Workbook

Sheet Dashboard
A1: PAINEL DE CONTROLE - IMPOSTO DE RENDA
A2: Organizador Inteligente para Declaração de Ajuste Anual
B4: TOTAL RENDIMENTOS BRUTOS | E4: TOTAL DEDUÇÕES INFORMADAS | H4: TOTAL IRRF RETIDO
B5: =SUM(Rendimentos!E4:E25) | E5: =SUM(Deducoes!F4:F25) | H5: =SUM(Rendimentos!F4:F25)
B8: RESUMO POR TIPO DE RENDIMENTO | F8: RESUMO DE DEDUÇÕES POR CATEGORIA
B9: Tipo | C9: Valor Total (R$) | D9: % do Total | F9: Categoria | G9: Valor Total (R$) | H9: % das Deduções
B10: Rendimento Tributável (Salário, Pro-labore, Aluguel) | C10: =SUMIF(Rendimentos!D$4:D$25, B10, Rendimentos!E$4:E$25) | D10: =IF($B$5>0, C10/$B$5, 0) | F10: Despesas Médicas | G10: =SUMIF(Deducoes!D$4:D$25, F10, Deducoes!F$4:F$25) | H10: =IF($E$5>0, G10/$E$5, 0)
B11: Rendimento Isento / Não Tributável (Lucros, Dividendos, Poupança) | C11: =SUMIF(Rendimentos!D$4:D$25, B11, Rendimentos!E$4:E$25) | D11: =IF($B$5>0, C11/$B$5, 0) | F11: Instrução / Educação | G11: =SUMIF(Deducoes!D$4:D$25, F11, Deducoes!F$4:F$25) | H11: =IF($E$5>0, G11/$E$5, 0)
B12: Tributação Exclusiva / Definitiva (13º Salário, PLR, Rend. Aplicações) | C12: =SUMIF(Rendimentos!D$4:D$25, B12, Rendimentos!E$4:E$25) | D12: =IF($B$5>0, C12/$B$5, 0) | F12: Previdência Privada (PGBL) | G12: =SUMIF(Deducoes!D$4:D$25, F12, Deducoes!F$4:F$25) | H12: =IF($E$5>0, G12/$E$5, 0)
F13: Pensão Alimentícia Judicial | G13: =SUMIF(Deducoes!D$4:D$25, F13, Deducoes!F$4:F$25) | H13: =IF($E$5>0, G13/$E$5, 0)
F14: Dependentes | G14: =SUMIF(Deducoes!D$4:D$25, F14, Deducoes!F$4:F$25) | H14: =IF($E$5>0, G14/$E$5, 0)
B15: EVOLUÇÃO PATRIMONIAL (BENS E DIREITOS) | F15: INSTRUÇÕES DE USO
B16: Patrimônio Total em 31/12/2024 | C16: =SUM(Bens_e_Direitos!D4:D25) | F16: 1. Alterne entre as abas na barra inferior para preencher seus dados.
B17: Patrimônio Total em 31/12/2025 | C17: =SUM(Bens_e_Direitos!E4:E25) | F17: 2. Utilize as listas suspensas (Validação de Dados) para selecionar os tipos.
B18: Variação Patrimonial | C18: =C17-C16 | F18: 3. Todos os valores no Dashboard são atualizados automaticamente via fórmulas.
F19: 4. Compatível 100% com o Microsoft Excel Online.

Sheet Rendimentos
A1: CONTROLE DE RENDIMENTOS - IMPOSTO DE RENDA
A3: ID | B3: Fonte Pagadora / Empresa | C3: CNPJ / CPF | D3: Tipo de Rendimento | E3: Valor Bruto (R$) | F3: IRRF Retido (R$) | G3: Status Documento
A4: 1 | B4: Empresa Tech LTDA | C4: 12.345.678/0001-90 | D4: Rendimento Tributável (Salário, Pro-labore, Aluguel) | E4: 85000 | F4: 11200 | G4: Comprovado
A5: 2 | B5: Banco de Investimentos SA | C5: 98.765.432/0001-10 | D5: Tributação Exclusiva / Definitiva (13º Salário, PLR, Rend. Aplicações) | E5: 7500 | F5: 1125 | G5: Comprovado
A6: 3 | B6: Consultoria Silva | C6: 11.222.333/0001-44 | D6: Rendimento Isento / Não Tributável (Lucros, Dividendos, Poupança) | E6: 15000 | F6: 0 | G6: Pendente
A7: 4
A8: 5
A9: 6
A10: 7
A11: 8
A12: 9
A13: 10
A14: 11
A15: 12
A16: 13
A17: 14
A18: 15
... A24: 21

Sheet Deducoes
A1: CONTROLE DE DEDUÇÕES E DESPESAS DEDUTÍVEIS
A3: ID | B3: Prestador / Beneficiário | C3: CPF / CNPJ | D3: Categoria da Despesa | E3: Descrição / Observação | F3: Valor Comprovado (R$) | G3: Status Recibo
A4: 1 | B4: Clínica Médica Saúde Total | C4: 00.111.222/0001-33 | D4: Despesas Médicas | E4: Consulta e Exames | F4: 3200 | G4: Comprovado
A5: 2 | B5: Faculdade / Escola Exemplo | C5: 33.444.555/0001-66 | D5: Instrução / Educação | E5: Mensalidades Pós-Graduação | F5: 2400 | G5: Comprovado
A6: 3 | B6: Bradesco Vida e Previdência | C6: 66.777.888/0001-99 | D6: Previdência Privada (PGBL) | E6: Aporte PGBL | F6: 5000 | G6: Comprovado
A7: 4
A8: 5
A9: 6
A10: 7
A11: 8
A12: 9
A13: 10
A14: 11
A15: 12
A16: 13
A17: 14
A18: 15
... A24: 21

Sheet Bens_e_Direitos
A1: DECLARAÇÃO DE BENS E DIREITOS
A3: ID | B3: Grupo / Categoria | C3: Discriminação / Descrição do Bem | D3: Situação em 31/12/2024 (R$) | E3: Situação em 31/12/2025 (R$)
A4: 1 | B4: Imóveis (Casa, Ap., Terreno) | C4: Apartamento Residencial em SP - 70m2 - Matrícula 12345 | D4: 350000 | E4: 350000
A5: 2 | B5: Veículos Automotores | C5: Automóvel Sedan 2.0 Flex Ano 2022 - Placa ABC1D23 | D5: 85000 | E5: 80000
A6: 3 | B6: Aplicações Financeiras / Renda Fixa | C6: CDB Banco YZ - 100% CDI | D6: 25000 | E6: 32000
A7: 4
A8: 5
A9: 6
A10: 7
A11: 8
A12: 9
A13: 10
A14: 11
A15: 12
A16: 13
A17: 14
A18: 15
... A24: 21

Sheet Categorias_Apoio
A1: Tipo Rendimento | B1: Tipo Dedução | C1: Tipo Bem
A2: Rendimento Tributável (Salário, Pro-labore, Aluguel) | B2: Despesas Médicas | C2: Imóveis (Casa, Ap., Terreno)
A3: Rendimento Isento / Não Tributável (Lucros, Dividendos, Poupança) | B3: Instrução / Educação | C3: Veículos Automotores
A4: Tributação Exclusiva / Definitiva (13º Salário, PLR, Rend. Aplicações) | B4: Previdência Privada (PGBL) | C4: Aplicações Financeiras / Renda Fixa
B5: Pensão Alimentícia Judicial | C5: Ações / Criptoativos
B6: Dependentes | C6: Saldos em Conta Corrente
